MANIFEST.in
README.rst
pytest_paste_config.py
setup.py
pytest_paste_config.egg-info/PKG-INFO
pytest_paste_config.egg-info/SOURCES.txt
pytest_paste_config.egg-info/dependency_links.txt
pytest_paste_config.egg-info/entry_points.txt
pytest_paste_config.egg-info/requires.txt
pytest_paste_config.egg-info/top_level.txt