Metadata-Version: 1.0
Name: pytest-paste-config
Version: 0.1
Summary: Allow setting the path to a paste config file
Home-page: UNKNOWN
Author: UNKNOWN
Author-email: UNKNOWN
License: MIT
Platform: UNKNOWN
Classifier: Development Status :: 3 - Alpha
Classifier: Topic :: Software Development :: Testing
Classifier: Intended Audience :: Developers
Classifier: Operating System :: OS Independent
